MANIFEST.in
README
README.md
setup.py
flask_restful_swagger/__init__.py
flask_restful_swagger/swagger.py
flask_restful_swagger.egg-info/PKG-INFO
flask_restful_swagger.egg-info/SOURCES.txt
flask_restful_swagger.egg-info/dependency_links.txt
flask_restful_swagger.egg-info/not-zip-safe
flask_restful_swagger.egg-info/requires.txt
flask_restful_swagger.egg-info/top_level.txt
flask_restful_swagger/static/endpoint.html
flask_restful_swagger/static/index.html
flask_restful_swagger/static/o2c.html
flask_restful_swagger/static/swagger-ui.js
flask_restful_swagger/static/swagger-ui.min.js
flask_restful_swagger/static/css/highlight.default.css
flask_restful_swagger/static/css/hightlight.default.css
flask_restful_swagger/static/css/screen.css
flask_restful_swagger/static/images/explorer_icons.png
flask_restful_swagger/static/images/logo_small.png
flask_restful_swagger/static/images/pet_store_api.png
flask_restful_swagger/static/images/throbber.gif
flask_restful_swagger/static/images/wordnik_api.png
flask_restful_swagger/static/lib/backbone-min.js
flask_restful_swagger/static/lib/handlebars-1.0.0.js
flask_restful_swagger/static/lib/highlight.7.3.pack.js
flask_restful_swagger/static/lib/jquery-1.8.0.min.js
flask_restful_swagger/static/lib/jquery.ba-bbq.min.js
flask_restful_swagger/static/lib/jquery.slideto.min.js
flask_restful_swagger/static/lib/jquery.wiggle.min.js
flask_restful_swagger/static/lib/shred.bundle.js
flask_restful_swagger/static/lib/swagger-oauth.js
flask_restful_swagger/static/lib/swagger.js
flask_restful_swagger/static/lib/underscore-min.js
flask_restful_swagger/static/lib/shred/content.js