Metadata-Version: 1.0
Name: flask-restful-swagger
Version: 0.13
Summary: Extrarct swagger specs from your flast-restful project
Home-page: https://github.com/rantav/flask-restful-swagger
Author: Ran Tavory
Author-email: UNKNOWN
License: MIT
Platform: UNKNOWN
